memory.v
module memory(dataOut,dataIn,address,reset,wr,clk);
parameter WIDTH = 32;//32 bits instruction
parameter ADDRSIZE = 12;//size of mem(# of data)
parameter MEMSIZE = (1<<ADDRSIZE);//(2^12)

input clk,reset,wr;
input [WIDTH-1:0]dataIn;
input [ADDRSIZE-1:0]address;
output reg [WIDTH-1:0]dataOut;
reg [WIDTH-1:0]MEM[0:MEMSIZE-1];

always @(posedge clk) begin
    if(reset) begin
        $readmemb("risc.prog", MEM);
    end
    else if(wr) begin
        MEM[address] = dataIn;
    end
    else begin
        dataOut = MEM[address] ;
    end    
end
endmodule

np_second_generation.v
/*==================================
* Model of RISC without pipeline.
* Three main task => fetch,execute,write
*/
// `timescale 1ns/10ps
module np(clk,reset,wr,address,dataIn,dataOut,halt);

parameter WIDTH = 32;//32 bits instruction
parameter ADDRSIZE = 12;//size of mem(# of data)
parameter MEMSIZE = (1<<ADDRSIZE) ;//(2^12)
parameter MAXREGS = 16;//Maximum # of registers
parameter SBITS = 5;//Status register bits
//Declare Registers ang Memory
reg [WIDTH-1:0]RFILE[0:MAXREGS-1],//Register file
               ir,// Instruction register
               src1,src2;// Alu operation registers
reg[WIDTH:0]result;// ALU result register
reg[SBITS-1:0]psr;// Processer counter for condition check
reg[ADDRSIZE-1:0]pc;// Program counter
reg dir;// Rotate direction

reg[1:0]state,next_state;//define the state of the cpu
integer i;
//define input and output
input clk,reset;
input [WIDTH-1:0]dataIn;
output reg [ADDRSIZE-1:0]address;
output reg [WIDTH-1:0]dataOut;
output reg wr,halt;
//wr : 1 for write 0 for read
// General definitions
`define TRUE 1
`define FALSE 0

// Define Instruction fields

`define OPCODE  ir[31:28]
`define SRC     ir[23:12]
`define DST     ir[11:0]
`define SRCTYPE ir[27]// source type 1 => imm 、0 => reg or mem
`define DSTTYPE ir[26]// destination type 1 => imm 、0 => reg or mem
`define CCODE   ir[27:24]//condition code for branch
`define SRCNT   ir[23:12]//Shift/rotate count -= left, +=right
// Operand Types
`define REGTYPE 0
`define IMMTYPE 1
// Define opcode for each instruction

`define NOP 4'b0000
`define BRA 4'b0001
`define STR 4'b0010
`define LD  4'b0011
`define ADD 4'b0100
`define MUL 4'b0101
`define CMP 4'b0110
`define SHF 4'b0111
`define ROT 4'b1000
`define SUB 4'b1001    // SUB R0 R1  <= R0 = R0 - R1
`define OR 4'b1010    // OR R0 R1  <= R0 = R0 or R1
`define HLT 4'b1011

// Define Condition code fields
`define CARRY  psr[0]
`define EVEN   psr[1]
`define PARITY psr[2]
`define ZERO   psr[3]
`define NEG    psr[4]

// Define Condition Code
`define CCC 1 // Result has carry
`define CCE 2 // Result is  even
`define CCP 3 // Result is  odd parity
`define CCZ 4 // Result is  zero
`define CCN 5 // Result is  negative
`define CCA 0 // Always

`define RIGHT 0// Rotate / Shift Right
`define LEFT  1// Rotate / Shift Left

parameter FET = 2'b00,EXE = 2'b01,WB = 2'b10;

// Function for ALU operands and result
function[WIDTH-1:0] getsrc;
input [WIDTH-1:0]in;
begin 
    if(`SRCTYPE == `REGTYPE) 
        getsrc = RFILE[`SRC];
    else 
        getsrc = `SRC;//immediate type
end
endfunction

function [WIDTH-1:0]getdst;
input [WIDTH-1:0]in;
begin
    if(`DSTTYPE == `REGTYPE)
        getdst = RFILE[`DST];
    else ;
end
endfunction

// Function / task for condition code
function checkcond;//Return 1 if conditon code is set
input[4:0]ccode;
begin
    case (ccode)
        `CCC:checkcond = `CARRY;
        `CCE:checkcond = `EVEN; 
        `CCP:checkcond = `PARITY; 
        `CCZ:checkcond = `ZERO; 
        `CCN:checkcond = `NEG; 
        `CCA:checkcond = 1; 
        default:checkcond = 0;
    endcase
end
endfunction

task clearcondcode;// Reset condition code in PSR
begin
    psr = 0;
end
endtask

task setcondcode;// Compute the condition codes and set PSR
input [WIDTH:0]res;//ALU result register
begin
    `CARRY = res[WIDTH];
    `EVEN = ~res[0];//check even
    `PARITY = ^res;//even # of 1 => 0, odd # of 1 => 1
    `ZERO = ~(|res);
    `NEG = res[WIDTH-1];
end
endtask

// Main Tasks - fetch execute write_result
task fetch;
begin
    wr = 0;
    address = pc;
    ir = dataIn;
    pc = pc + 1;
end
endtask

task execute;
begin
    case (`OPCODE)
    `NOP: ;
    `BRA: begin
        if(checkcond(`CCODE)==1)
            pc = `DST; 
    end
    `LD: begin
        clearcondcode;
        if(`SRCTYPE == `IMMTYPE) begin
            result = `SRC;
        end
        else begin
            wr = 0;
            address = `SRC;
            result = dataIn;
        end
        setcondcode(result);
    end
    `STR: begin
        clearcondcode;
        wr = 1;
        address = `DST;
        if(`SRCTYPE == `IMMTYPE) 
            result = `SRC;
        else 
            result = RFILE[`SRC];
        if(`SRCTYPE == `IMMTYPE)
            setcondcode(result);
        else
            setcondcode(result);
    end
    `ADD: begin
        clearcondcode;
        src1 = getsrc(ir);
        src2 = getdst(ir);
        result = src1 + src2;
        setcondcode(result);
    end
    `MUL: begin
        clearcondcode;
        src1 = getsrc(ir);
        src2 = getdst(ir);
        result = src1 * src2;
        setcondcode(result);
    end
    `CMP: begin // complement
        clearcondcode;
        src1 = getsrc(ir);
        result = ~src1;
        setcondcode(result);
    end
    `SHF:begin
        clearcondcode;
        src1 = getsrc(ir);
        src2 = getdst(ir);
        i = (src1[ADDRSIZE-1]>=0)?src1:-src1[ADDRSIZE-1:0];
        result = (i>0)?(src2>>i):(src2<<-i);
        setcondcode(result);
    end
    `ROT:begin
        clearcondcode;
        src1 = getsrc(ir);
        src2 = getdst(ir);  
        dir = src1[ADDRSIZE-1] >=0 ?`RIGHT:`LEFT;
        i = (src1[ADDRSIZE-1]>=0)?src1:-src1[ADDRSIZE-1:0];
        while(i > 0)begin
            if(dir==`RIGHT)begin
                result = src2 >> 1;
                result[WIDTH-1] = src2[0];
            end
            else begin
                result = src2 << 1;
                result[0] = src2[WIDTH-1]; 
            end
            i = i - 1;
            src2 = result;
        end
        setcondcode(result);
    end
    `SUB: begin
        clearcondcode;
        src1 = getsrc(ir);
        src2 = getdst(ir);
        result = src2 - src1;
        setcondcode(result);
      end
     `OR: begin
        clearcondcode;
        src1 = getsrc(ir);
        src2 = getdst(ir);
        result = src2 | src1;
        setcondcode(result);
      end
    `HLT: begin
        halt = 1;        
        // $display("Halt...");
        // $finish;
    end
    default:;
    endcase
end
endtask

//Write the result in register file or memory
task write_result;
begin    
    if((`OPCODE >= `LD) && (`OPCODE < `HLT))begin
        if(`DSTTYPE == `REGTYPE)begin
            RFILE[`DST] = result;
        end
        else begin
            $display("error!!");
        end
    end
    else if((`OPCODE == `STR))begin
        dataOut = result[31:0];
    end
end
endtask

always@(*)begin
    $display("%d %d %b %b", $time, pc, RFILE[0], RFILE[1]);
end

always @(posedge clk) begin
    if(reset) begin
        wr <= 0;
        next_state <= FET;
        pc <= 0;
        halt <= 0;
    end
    else begin
        state <= next_state;
        $display("%d",pc);
    end
end

always @(state) begin
	case(state)	
	FET:begin
        fetch;
        next_state = EXE;
    end
	EXE:begin
        execute;
        next_state = WB;
    end
	WB:begin
        write_result;
        next_state = FET;
    end
	default:next_state = FET;	
	endcase	
end

endmodule

testbench.v
`timescale 1ns/10ps
`ifdef syn
`include "tsmc18.v"
`include "np_sync.v"
`else
`include "np_second_generation.v"
`include "memory.v"
`endif
//---------------------------------------------------------------------------------------------------------
module test;
parameter WIDTH = 32;//32 bits instruction
parameter ADDRSIZE = 12;//size of mem(# of data)
parameter MEMSIZE = (1<<ADDRSIZE) ;//(2^12)
parameter CYCLE = 10;//clock time
reg clk,reset;
wire[WIDTH-1:0]CPU_dataIn;
wire [WIDTH-1:0]CPU_dataOut;
wire[ADDRSIZE-1:0]address;
wire wr,halt;
np mnp(.clk(clk),.reset(reset),.wr(wr),.address(address),.dataIn(CPU_dataIn),.dataOut(CPU_dataOut),.halt(halt));
memory mem(.dataOut(CPU_dataIn),.dataIn(CPU_dataOut),.address(address),.reset(reset),.wr(wr),.clk(clk));
//---------------------------------------------------------------------------------------------------------

//---------------------------------------------------------------------------------------------------------
`ifdef syn
initial $sdf_annotate ("np_sync.sdf", tff);
`endif
//---------------------------------------------------------------------------------------------------------
//begin the clk
initial
begin
  clk = 0;
  reset = 1;
  #(3*CYCLE) reset = 0;
end

always #(CYCLE/2) clk = ~clk;
//---------------------------------------------------------------------------------------------------------
always @(halt) begin
  if(halt)begin
    $display("halt");
    $finish;
  end
end
//---------------------------------------------------------------------------------------------------------

`ifdef syn
initial begin
	$dumpfile("np_sync.vcd");
	$dumpvars;
end
`else
initial begin
	$dumpfile("np.vcd");
	$dumpvars;
end
`endif

endmodule

np.vcd
$date
	Sat Dec 07 01:17:30 2019
$end
$version
	Icarus Verilog
$end
$timescale
	10ps
$end
$scope module test $end
$var wire 1 ! wr $end
$var wire 1 " halt $end
$var wire 12 # address [11:0] $end
$var wire 32 $ CPU_dataOut [31:0] $end
$var wire 32 % CPU_dataIn [31:0] $end
$var reg 1 & clk $end
$var reg 1 ' reset $end
$scope module mem $end
$var wire 1 & clk $end
$var wire 1 ' reset $end
$var wire 1 ! wr $end
$var wire 32 ( dataIn [31:0] $end
$var wire 12 ) address [11:0] $end
$var reg 32 * dataOut [31:0] $end
$upscope $end
$scope module mnp $end
$var wire 1 & clk $end
$var wire 32 + dataIn [31:0] $end
$var wire 1 ' reset $end
$var reg 12 , address [11:0] $end
$var reg 32 - dataOut [31:0] $end
$var reg 1 . dir $end
$var reg 1 " halt $end
$var reg 32 / ir [31:0] $end
$var reg 2 0 next_state [1:0] $end
$var reg 12 1 pc [11:0] $end
$var reg 5 2 psr [4:0] $end
$var reg 33 3 result [32:0] $end
$var reg 32 4 src1 [31:0] $end
$var reg 32 5 src2 [31:0] $end
$var reg 2 6 state [1:0] $end
$var reg 1 ! wr $end
$var integer 32 7 i [31:0] $end
$scope function checkcond $end
$var reg 5 8 ccode [4:0] $end
$var reg 1 9 checkcond $end
$upscope $end
$scope function getdst $end
$var reg 32 : getdst [31:0] $end
$var reg 32 ; in [31:0] $end
$upscope $end
$scope function getsrc $end
$var reg 32 < getsrc [31:0] $end
$var reg 32 = in [31:0] $end
$upscope $end
$scope task clearcondcode $end
$upscope $end
$scope task execute $end
$upscope $end
$scope task fetch $end
$upscope $end
$scope task setcondcode $end
$var reg 33 > res [32:0] $end
$upscope $end
$scope task write_result $end
$upscope $end
$upscope $end
$upscope $end
$enddefinitions $end
#0
$dumpvars
bx >
bx =
bx <
bx ;
bx :
x9
bx 8
bx 7
bx 6
bx 5
bx 4
bx 3
bx 2
bx 1
bx 0
bx /
x.
bx -
bx ,
bx +
bx *
bx )
bx (
1'
0&
bx %
bx $
bx #
x"
x!
$end
#500
0"
b0 1
b0 0
0!
1&
#1000
0&
#1500
1&
#2000
0&
#2500
1&
#3000
0&
0'
#3500
b1 0
b1 1
b0 #
b0 )
b0 ,
b0 6
1&
#4000
0&
#4500
b10 0
b1 6
b0 %
b0 *
b0 +
1&
#5000
0&
#5500
b0 0
b10 6
1&
#6000
0&
#6500
b1 0
b10 1
b0 /
b1 #
b1 )
b1 ,
b0 6
1&
#7000
0&
#7500
b10 0
b1 6
b10000000000000000000000000011 %
b10000000000000000000000000011 *
b10000000000000000000000000011 +
1&
#8000
0&
#8500
b0 0
b10 6
1&
#9000
0&
#9500
b1 0
b11 1
b10000000000000000000000000011 /
b10 #
b10 )
b10 ,
b0 6
1&
#10000
0&
#10500
b10 0
19
b0 8
b1 6
b0 %
b0 *
b0 +
1&
#11000
0&
#11500
b0 0
b10 6
1&
#12000
0&
#12500
b1 0
b100 1
b0 /
b11 #
b11 )
b11 ,
b0 6
1&
#13000
0&
#13500
b10 0
b1 6
b111000000000000010000000000000 %
b111000000000000010000000000000 *
b111000000000000010000000000000 +
1&
#14000
0&
#14500
b0 0
b10 6
1&
#15000
0&
#15500
b1 0
b101 1
b111000000000000010000000000000 /
b100 #
b100 )
b100 ,
b0 6
1&
#16000
0&
#16500
b10 0
b10 >
b10 3
b110 2
b1 6
b100000000000000000100000000000 %
b100000000000000000100000000000 *
b100000000000000000100000000000 +
1&
#17000
0&
#17500
b0 0
b10 6
1&
#18000
0&
#18500
b1 0
b110 1
b100000000000000000100000000000 /
b101 #
b101 )
b101 ,
b0 6
1&
#19000
0&
#19500
b10 0
b100000000000 #
b100000000000 )
b100000000000 ,
1!
b110 2
b1 6
b111000000000000000000000000000 %
b111000000000000000000000000000 *
b111000000000000000000000000000 +
1&
#20000
0&
#20500
b0 0
b10 $
b10 (
b10 -
b10 6
1&
#21000
0&
#21500
b1 0
b111 1
b111000000000000000000000000000 /
b110 #
b110 )
b110 ,
0!
b0 6
1&
#22000
0&
#22500
b10 0
b0 >
b0 3
b1010 2
b1 6
b110000100000000000000000000000 %
b110000100000000000000000000000 *
b110000100000000000000000000000 +
1&
#23000
0&
#23500
b0 0
b10 6
1&
#24000
0&
#24500
b1 0
b1000 1
b110000100000000000000000000000 /
b111 #
b111 )
b111 ,
b0 6
1&
#25000
0&
#25500
b10 0
b111000000000000000000000000000 >
b111000000000000000000000000000 3
b100000000000 #
b100000000000 )
b100000000000 ,
b110 2
b1 6
b111000000000000000000000000000 %
b111000000000000000000000000000 *
b111000000000000000000000000000 +
1&
#26000
0&
#26500
b0 0
b10 6
b10 %
b10 *
b10 +
1&
#27000
0&
#27500
b1 0
b1001 1
b10 /
b1000 #
b1000 )
b1000 ,
b0 6
1&
#28000
0&
#28500
b10 0
b1 6
b1001000000000000100000000000000 %
b1001000000000000100000000000000 *
b1001000000000000100000000000000 +
1&
#29000
0&
#29500
b0 0
b10 6
1&
#30000
0&
#30500
b1 0
b1010 1
b1001000000000000100000000000000 /
b1001 #
b1001 )
b1001 ,
b0 6
1&
#31000
0&
#31500
b10 0
b111000000000000000000000000100 >
b111000000000000000000000000100 3
b111000000000000000000000000000 5
b111000000000000000000000000000 :
b1001000000000000100000000000000 ;
b100 4
b100 <
b1001000000000000100000000000000 =
b10 2
b1 6
b111000000000000010000000000000 %
b111000000000000010000000000000 *
b111000000000000010000000000000 +
1&
#32000
0&
#32500
b0 0
b10 6
1&
#33000
0&
#33500
b1 0
b1011 1
b111000000000000010000000000000 /
b1010 #
b1010 )
b1010 ,
b0 6
1&
#34000
0&
#34500
b10 0
b10 >
b10 3
b110 2
b1 6
b1011000000000000100000000000000 %
b1011000000000000100000000000000 *
b1011000000000000100000000000000 +
1&
#35000
0&
#35500
b0 0
b10 6
1&
#36000
0&
#36500
b1 0
b1100 1
b1011000000000000100000000000000 /
b1011 #
b1011 )
b1011 ,
b0 6
1&
#37000
0&
#37500
b10 0
b1000 >
b1000 3
b10 5
b10 :
b1011000000000000100000000000000 ;
b1011000000000000100000000000000 =
b110 2
b1 6
b1100000000000000000000000000001 %
b1100000000000000000000000000001 *
b1100000000000000000000000000001 +
1&
#38000
0&
#38500
b0 0
b10 6
1&
#39000
0&
#39500
b1 0
b1101 1
b1100000000000000000000000000001 /
b1100 #
b1100 )
b1100 ,
b0 6
1&
#40000
0&
#40500
b10 0
b111111111111111111111111111110111 >
b111111111111111111111111111110111 3
b1000 4
b1000 <
b1100000000000000000000000000001 =
b10001 2
b1 6
b111000000000001111000000000000 %
b111000000000001111000000000000 *
b111000000000001111000000000000 +
1&
#41000
0&
#41500
b0 0
b10 6
1&
#42000
0&
#42500
b1 0
b1110 1
b111000000000001111000000000000 /
b1101 #
b1101 )
b1101 ,
b0 6
1&
#43000
0&
#43500
b10 0
b1111 >
b1111 3
b0 2
b1 6
b111000000000000000000000000001 %
b111000000000000000000000000001 *
b111000000000000000000000000001 +
1&
#44000
0&
#44500
b0 0
b10 6
1&
#45000
0&
#45500
b1 0
b1111 1
b111000000000000000000000000001 /
b1110 #
b1110 )
b1110 ,
b0 6
1&
#46000
0&
#46500
b10 0
b1010 2
b0 >
b0 3
b1 6
b10011000000000000001000000000001 %
b10011000000000000001000000000001 *
b10011000000000000001000000000001 +
1&
#47000
0&
#47500
b0 0
b10 6
1&
#48000
0&
#48500
b1 0
b10000 1
b10011000000000000001000000000001 /
b1111 #
b1111 )
b1111 ,
b0 6
1&
#49000
0&
#49500
b10 0
b111111111111111111111111111111111 >
b111111111111111111111111111111111 3
b0 5
b0 :
b10011000000000000001000000000001 ;
b1 4
b1 <
b10011000000000000001000000000001 =
b10101 2
b1 6
b1110000000000000001000000000000 %
b1110000000000000001000000000000 *
b1110000000000000001000000000000 +
1&
#50000
0&
#50500
b0 0
b10 6
1&
#51000
0&
#51500
b1 0
b10001 1
b1110000000000000001000000000000 /
b10000 #
b10000 )
b10000 ,
b0 6
1&
#52000
0&
#52500
b10 0
b11110 >
b11110 3
b11111111111111111111111111111111 7
b1111 5
b1111 :
b1110000000000000001000000000000 ;
b11111111111111111111111111111111 4
b11111111111111111111111111111111 <
b1110000000000000001000000000000 =
b10 2
b1 6
b1111000000000000001000000000000 %
b1111000000000000001000000000000 *
b1111000000000000001000000000000 +
1&
#53000
0&
#53500
b0 0
b10 6
1&
#54000
0&
#54500
b1 0
b10010 1
b1111000000000000001000000000000 /
b10001 #
b10001 )
b10001 ,
b0 6
1&
#55000
0&
#55500
b10 0
b1111 >
b1111 3
b1 7
b11110 5
b11110 :
b1111000000000000001000000000000 ;
b1 4
b1 <
b1111000000000000001000000000000 =
b0 2
b1 6
b111000000000000001000000000000 %
b111000000000000001000000000000 *
b111000000000000001000000000000 +
1&
#56000
0&
#56500
b0 0
b10 6
1&
#57000
0&
#57500
b1 0
b10011 1
b111000000000000001000000000000 /
b10010 #
b10010 )
b10010 ,
b0 6
1&
#58000
0&
#58500
b10 0
b100 2
b1 >
b1 3
b1 6
b111000000000000000000000000001 %
b111000000000000000000000000001 *
b111000000000000000000000000001 +
1&
#59000
0&
#59500
b0 0
b10 6
1&
#60000
0&
#60500
b1 0
b10100 1
b111000000000000000000000000001 /
b10011 #
b10011 )
b10011 ,
b0 6
1&
#61000
0&
#61500
b10 0
b0 >
b0 3
b1010 2
b1 6
b10011000000000011111000000000001 %
b10011000000000011111000000000001 *
b10011000000000011111000000000001 +
1&
#62000
0&
#62500
b0 0
b10 6
1&
#63000
0&
#63500
b1 0
b10101 1
b10011000000000011111000000000001 /
b10100 #
b10100 )
b10100 ,
b0 6
1&
#64000
0&
#64500
b10 0
b111111111111111111111111111100001 >
b111111111111111111111111111100001 3
b0 5
b0 :
b10011000000000011111000000000001 ;
b11111 4
b11111 <
b10011000000000011111000000000001 =
b10101 2
b1 6
b1110000000000000001000000000000 %
b1110000000000000001000000000000 *
b1110000000000000001000000000000 +
1&
#65000
0&
#65500
b0 0
b10 6
1&
#66000
0&
#66500
b1 0
b10110 1
b1110000000000000001000000000000 /
b10101 #
b10101 )
b10101 ,
b0 6
1&
#67000
0&
#67500
b10 0
b10000000000000000000000000000000 >
b10000000000000000000000000000000 3
b11111111111111111111111111100001 7
b1 5
b1 :
b1110000000000000001000000000000 ;
b11111111111111111111111111100001 4
b11111111111111111111111111100001 <
b1110000000000000001000000000000 =
b10110 2
b1 6
b10001000000000000001000000000000 %
b10001000000000000001000000000000 *
b10001000000000000001000000000000 +
1&
#68000
0&
#68500
b0 0
b10 6
1&
#69000
0&
#69500
b1 0
b10111 1
b10001000000000000001000000000000 /
b10110 #
b10110 )
b10110 ,
b0 6
1&
#70000
0&
#70500
b10 0
b1000000000000000000000000000000 >
b1000000000000000000000000000000 3
b0 7
0.
b1000000000000000000000000000000 5
b10000000000000000000000000000000 :
b10001000000000000001000000000000 ;
b1 4
b1 <
b10001000000000000001000000000000 =
b110 2
b1 6
b111000000000010000000000000000 %
b111000000000010000000000000000 *
b111000000000010000000000000000 +
1&
#71000
0&
#71500
b0 0
b10 6
1&
#72000
0&
#72500
b1 0
b11000 1
b111000000000010000000000000000 /
b10111 #
b10111 )
b10111 ,
b0 6
1&
#73000
0&
#73500
b10 0
b10000 >
b10000 3
b110 2
b1 6
b10011000000000000100000000000000 %
b10011000000000000100000000000000 *
b10011000000000000100000000000000 +
1&
#74000
0&
#74500
b0 0
b10 6
1&
#75000
0&
#75500
b1 0
b11001 1
b10011000000000000100000000000000 /
b11000 #
b11000 )
b11000 ,
b0 6
1&
#76000
0&
#76500
b10 0
b1100 >
b1100 3
b10000 5
b10000 :
b10011000000000000100000000000000 ;
b100 4
b100 <
b10011000000000000100000000000000 =
b10 2
b1 6
b111000000000010000000000000000 %
b111000000000010000000000000000 *
b111000000000010000000000000000 +
1&
#77000
0&
#77500
b0 0
b10 6
1&
#78000
0&
#78500
b1 0
b11010 1
b111000000000010000000000000000 /
b11001 #
b11001 )
b11001 ,
b0 6
1&
#79000
0&
#79500
b10 0
b10000 >
b10000 3
b110 2
b1 6
b111000000000010001000000000001 %
b111000000000010001000000000001 *
b111000000000010001000000000001 +
1&
#80000
0&
#80500
b0 0
b10 6
1&
#81000
0&
#81500
b1 0
b11011 1
b111000000000010001000000000001 /
b11010 #
b11010 )
b11010 ,
b0 6
1&
#82000
0&
#82500
b10 0
b10001 >
b10001 3
b0 2
b1 6
b10100000000000000001000000000000 %
b10100000000000000001000000000000 *
b10100000000000000001000000000000 +
1&
#83000
0&
#83500
b0 0
b10 6
1&
#84000
0&
#84500
b1 0
b11100 1
b10100000000000000001000000000000 /
b11011 #
b11011 )
b11011 ,
b0 6
1&
#85000
0&
#85500
b10 0
b10100000000000000001000000000000 ;
b10001 4
b10001 <
b10100000000000000001000000000000 =
b1 6
b10111111111111111111111111111111 %
b10111111111111111111111111111111 *
b10111111111111111111111111111111 +
1&
#86000
0&
#86500
b0 0
b10 6
1&
#87000
0&
#87500
b1 0
b11101 1
b10111111111111111111111111111111 /
b11100 #
b11100 )
b11100 ,
b0 6
1&
#88000
0&
#88500
b10 0
1"
b1 6
bx %
bx *
bx +
1&
