inMemory.v
module inMemory(dataOut,dataIn,address,reset,wr,clk);
parameter WIDTH = 32;//32 bits instruction
parameter ADDRSIZE = 12;//size of mem(# of data)
parameter MEMSIZE = (1<<ADDRSIZE);//(2^12)

input clk,reset,wr;
input [WIDTH-1:0]dataIn;
input [ADDRSIZE-1:0]address;
output reg [WIDTH-1:0]dataOut;
reg [WIDTH-1:0]MEM[0:MEMSIZE-1];

always @(posedge clk) begin
    if(reset) begin
        $readmemb("risc.prog", MEM);
    end
    else if(wr) begin
        MEM[address] = dataIn;
    end
    else begin
        dataOut = MEM[address] ;
    end    
end
endmodule

memory.v
module memory(dataOut,dataIn,address,reset,wr,clk);
parameter WIDTH = 32;//32 bits instruction
parameter ADDRSIZE = 12;//size of mem(# of data)
parameter MEMSIZE = (1<<ADDRSIZE);//(2^12)

input clk,reset,wr;
input [WIDTH-1:0]dataIn;
input [ADDRSIZE-1:0]address;
output reg [WIDTH-1:0]dataOut;
reg [WIDTH-1:0]MEM[0:MEMSIZE-1];

always @(posedge clk) begin
    if(reset) begin
        $readmemb("risc.prog", MEM);
    end
    else if(wr) begin
        MEM[address] = dataIn;
    end
    else begin
        dataOut = MEM[address] ;
    end    
end
endmodule

np_second_generation.v
/*==================================
* Model of RISC without pipeline.
* Three main task => fetch,execute,write
*/
// `timescale 1ns/10ps
module np(clk,reset,in_wr,wr,in_address,in_dataIn,in_dataOut,address,dataIn,dataOut,halt);

parameter WIDTH = 32;//32 bits instruction
parameter ADDRSIZE = 12;//size of mem(# of data)
parameter MEMSIZE = (1<<ADDRSIZE) ;//(2^12)
parameter MAXREGS = 16;//Maximum # of registers
parameter SBITS = 5;//Status register bits
//Declare Registers ang Memory
reg [WIDTH-1:0]RFILE[0:MAXREGS-1],//Register file
               ir,// Instruction register
               src1,src2;// Alu operation registers
reg [WIDTH-1:0]RFILE_r[0:MAXREGS-1];//Register file
reg[WIDTH:0]result;// ALU result register
reg[SBITS-1:0]psr;// Processer counter for condition check
reg[ADDRSIZE-1:0]pc;// Program counter
reg dir;// Rotate direction
reg[ADDRSIZE-1:0]pc_r;
reg [WIDTH-1:0]ir_r;// Instruction register
reg[WIDTH:0]result_r;// ALU result register
reg[SBITS-1:0]psr_r;// Processer counter for condition check
reg[1:0]state,next_state;//define the state of the cpu

integer i;
//define input and output
input clk,reset;
input [WIDTH-1:0]in_dataIn;
input [WIDTH-1:0]dataIn;
output reg [ADDRSIZE-1:0]in_address;
output reg [ADDRSIZE-1:0]address;
output reg [WIDTH-1:0]in_dataOut;
output reg [WIDTH-1:0]dataOut;
output reg wr,in_wr,halt;
//wr : 1 for write 0 for read
// General definitions
`define TRUE 1
`define FALSE 0

// Define Instruction fields

`define OPCODE  ir[31:28]
`define SRC     ir[23:12]
`define DST     ir[11:0]
`define SRCTYPE ir[27]// source type 1 => imm 、0 => reg or mem
`define DSTTYPE ir[26]// destin_ation type 1 => imm 、0 => reg or mem
`define CCODE   ir[27:24]//condition code for branch
`define SRCNT   ir[23:12]//Shift/rotate count -= left, +=right
// Operand Types
`define REGTYPE 0
`define IMMTYPE 1
// Define opcode for each instruction

`define NOP 4'b0000
`define BRA 4'b0001
`define STR 4'b0010
`define LD  4'b0011
`define ADD 4'b0100
`define MUL 4'b0101
`define CMP 4'b0110
`define SHF 4'b0111
`define ROT 4'b1000
`define SUB 4'b1001    // SUB R0 R1  <= R0 = R0 - R1
`define OR 4'b1010    // OR R0 R1  <= R0 = R0 or R1
`define HLT 4'b1011

// Define Condition code fields
`define CARRY  psr[0]
`define EVEN   psr[1]
`define PARITY psr[2]
`define ZERO   psr[3]
`define NEG    psr[4]

// Define Condition Code
`define CCC 1 // Result has carry
`define CCE 2 // Result is  even
`define CCP 3 // Result is  odd parity
`define CCZ 4 // Result is  zero
`define CCN 5 // Result is  negative
`define CCA 0 // Always

`define RIGHT 0// Rotate / Shift Right
`define LEFT  1// Rotate / Shift Left

parameter FET = 2'b00,EXE = 2'b01,WB = 2'b10,RESET = 2'b11;

// Function for ALU operands and result
function[WIDTH-1:0] getsrc;
input [WIDTH-1:0]in;
begin 
    if(`SRCTYPE == `REGTYPE) 
        getsrc = RFILE[`SRC];
    else 
        getsrc = `SRC;//immediate type
end
endfunction

function [WIDTH-1:0]getdst;
input [WIDTH-1:0]in;
begin
    if(`DSTTYPE == `REGTYPE)
        getdst = RFILE[`DST];
    else ;
end
endfunction

// Function / task for condition code
function checkcond;//Return 1 if conditon code is set
input[4:0]ccode;
begin
    case (ccode)
        `CCC:checkcond = `CARRY;
        `CCE:checkcond = `EVEN; 
        `CCP:checkcond = `PARITY; 
        `CCZ:checkcond = `ZERO; 
        `CCN:checkcond = `NEG; 
        `CCA:checkcond = 1; 
        default:checkcond = 0;
    endcase
end
endfunction

task clearcondcode;// Reset condition code in PSR
begin
    psr = 0;
end
endtask

task setcondcode;// Compute the condition codes and set PSR
input [WIDTH:0]res;//ALU result register
begin
    `CARRY = res[WIDTH];
    `EVEN = ~res[0];//check even
    `PARITY = ^res;//even # of 1 => 0, odd # of 1 => 1
    `ZERO = ~(|res);
    `NEG = res[WIDTH-1];
end
endtask

// Main Tasks - fetch execute write_result
task fetch;
begin
    in_wr = 0;
    ir = in_dataIn;
end
endtask

task execute;
begin
    case (`OPCODE)
    `NOP: ;
    `BRA: begin
        if(checkcond(`CCODE)==1)begin
            pc = `DST; 
            $display("bra");
        end
    end
    `LD: begin
        clearcondcode;
        $display("LD");
        if(`SRCTYPE == `IMMTYPE) begin
            result = `SRC;
        end
        else begin
            wr = 0;
            address = `SRC;
        end
        //setcondcode(result);
    end
    `STR: begin
        clearcondcode;
        wr = 1;
        address = `DST;
        if(`SRCTYPE == `IMMTYPE) 
            result = `SRC;
        else 
            result = RFILE[`SRC];
        //setcondcode(result);
    end
    `ADD: begin
        clearcondcode;
        src1 = getsrc(ir);
        src2 = getdst(ir);
        result = src1 + src2;
        //setcondcode(result);
    end
    `MUL: begin
        clearcondcode;
        src1 = getsrc(ir);
        src2 = getdst(ir);
        result = src1 * src2;
        //setcondcode(result);
    end
    `CMP: begin // complement
        clearcondcode;
        src1 = getsrc(ir);
        result = ~src1;
        //setcondcode(result);
    end
    `SHF:begin // test it
        clearcondcode;
        src1 = getsrc(ir);
        src2 = getdst(ir);
        i = (src1[ADDRSIZE-1]>=0)?src1:-src1[ADDRSIZE-1:0];
        result = (i>0)?(src2>>i):(src2<<-i);
        //setcondcode(result);
    end
    `ROT:begin // rebuild it
        clearcondcode;
        src1 = getsrc(ir);
        src2 = getdst(ir);  
        dir = src1[ADDRSIZE-1] >=0 ?`RIGHT:`LEFT;
        i = (src1[ADDRSIZE-1]>=0)?src1:-src1[ADDRSIZE-1:0];
        while(i > 0)begin
            if(dir==`RIGHT)begin
                result = src2 >> 1;
                result[WIDTH-1] = src2[0];
            end
            else begin
                result = src2 << 1;
                result[0] = src2[WIDTH-1]; 
            end
            i = i - 1;
            src2 = result;
        end
        //setcondcode(result);
    end
    `SUB: begin
        clearcondcode;
        src1 = getsrc(ir);
        src2 = getdst(ir);
        result = src2 - src1;
        //setcondcode(result);
      end
     `OR: begin
        clearcondcode;
        src1 = getsrc(ir);
        src2 = getdst(ir);
        result = src2 | src1;
        //setcondcode(result);
      end
    `HLT: begin
        halt = 1;        
        // $display("Halt...");
        // $finish;
    end
    default:;
    endcase
end
endtask

//Write the result in register file or memory
task write_result;
begin    
    if((`OPCODE >= `ADD) && (`OPCODE < `HLT))begin
        if(`DSTTYPE == `REGTYPE)begin
            RFILE[`DST] = result;
        end
        else begin
            $display("error!!");
        end
        setcondcode(result);
    end
    else if((`OPCODE == `LD))begin
        if(`SRCTYPE != `IMMTYPE) begin // load from datamemory
            wr = 0;
            address = `SRC;
            result = dataIn;
        end
        if(`DSTTYPE == `REGTYPE)begin
            RFILE[`DST] = result;
        end
        else begin
            $display("error!!");
        end
        setcondcode(result);
    end
    else if((`OPCODE == `STR))begin // store the value to memory
        wr = 1;
        address = `DST;
        dataOut = result[31:0];
        setcondcode(result);
    end

    if(!(`OPCODE == `BRA))begin 
        pc = pc_r + 1;//next instruction ,preassign instruction address       
    end
end
endtask

always@(*)begin
    $display("%d %d %h %h", $time, pc, RFILE[0], RFILE[1]);
end

always @(posedge clk) begin
    if(reset) begin
        state <= RESET;
        pc_r <= 0;
        result_r <= 0;
        psr_r <= 0;
        //
        RFILE_r[0] <= 0;
        RFILE_r[1] <= 0;
        RFILE_r[2] <= 0;
        RFILE_r[3] <= 0;
        RFILE_r[4] <= 0;
        RFILE_r[5] <= 0;
        RFILE_r[6] <= 0;
        RFILE_r[7] <= 0;
        RFILE_r[8] <= 0;
        RFILE_r[9] <= 0;
        RFILE_r[10] <= 0;
        RFILE_r[11] <= 0;
        RFILE_r[12] <= 0;
        RFILE_r[13] <= 0;
        RFILE_r[14] <= 0;
        RFILE_r[15] <= 0;        
    end
    else begin
        pc_r <= pc;
        result_r <= result;
        state <= next_state;
        psr_r <= psr;
        //
        RFILE_r[0] <= RFILE[0];
        RFILE_r[1] <= RFILE[1];
        RFILE_r[2] <= RFILE[2];
        RFILE_r[3] <= RFILE[3];
        RFILE_r[4] <= RFILE[4];
        RFILE_r[5] <= RFILE[5];
        RFILE_r[6] <= RFILE[6];
        RFILE_r[7] <= RFILE[7];
        RFILE_r[8] <= RFILE[8];
        RFILE_r[9] <= RFILE[9];
        RFILE_r[10] <= RFILE[10];
        RFILE_r[11] <= RFILE[11];
        RFILE_r[12] <= RFILE[12];
        RFILE_r[13] <= RFILE[13];
        RFILE_r[14] <= RFILE[14];
        RFILE_r[15] <= RFILE[15];
    end
end

always @(state) begin
    pc = pc_r;
    halt = 0;
    in_wr = 0;
    wr = 0;
    address = 0;
    in_address = pc;
    ir = in_dataIn;
    dataOut = 0;
    src1 = 0;
    src2 = 0;
    result = result_r;
    psr = psr_r;
    
    RFILE[0] = RFILE_r[0];
    RFILE[1] = RFILE_r[1];
    RFILE[2] = RFILE_r[2];
    RFILE[3] = RFILE_r[3];
    RFILE[4] = RFILE_r[4];
    RFILE[5] = RFILE_r[5];
    RFILE[6] = RFILE_r[6];
    RFILE[7] = RFILE_r[7];
    RFILE[8] = RFILE_r[8];
    RFILE[9] = RFILE_r[9];
    RFILE[10] = RFILE_r[10];
    RFILE[11] = RFILE_r[11];
    RFILE[12] = RFILE_r[12];
    RFILE[13] = RFILE_r[13];
    RFILE[14] = RFILE_r[14];
    RFILE[15] = RFILE_r[15];
    /*
    reg [WIDTH-1:0]RFILE[0:MAXREGS-1],//Register file
    */
	case(state)	
	FET:begin
        fetch;
        next_state = EXE;
    end
	EXE:begin
        execute;
        next_state = WB;
    end
	WB:begin
        write_result;
        next_state = FET;
    end
	default:begin // for reset
        next_state = FET;
        pc = 0;	
    end
	endcase	
end

endmodule

testbench.v
`timescale 1ns/10ps
`ifdef syn
`include "tsmc18.v"
`include "np_sync.v"
`else
`include "np_second_generation.v"
`include "memory.v"
`include "inMemory.v"

`endif
//---------------------------------------------------------------------------------------------------------
module test;
parameter WIDTH = 32;//32 bits instruction
parameter ADDRSIZE = 12;//size of mem(# of data)
parameter MEMSIZE = (1<<ADDRSIZE) ;//(2^12)
parameter CYCLE = 10;//clock time
reg clk,reset;
wire[WIDTH-1:0]CPU_dataIn;
wire [WIDTH-1:0]CPU_dataOut;
wire[ADDRSIZE-1:0]address;
wire[WIDTH-1:0]CPU_in_dataIn;
wire [WIDTH-1:0]CPU_in_dataOut;
wire[ADDRSIZE-1:0]in_address;
wire in_wr,wr,halt;
np mnp(.clk(clk),.reset(reset),.address(address),.dataIn(CPU_dataIn),.dataOut(CPU_dataOut),.wr(wr),
.in_wr(in_wr),.in_address(in_address),.in_dataIn(CPU_in_dataIn),.in_dataOut(CPU_in_dataOut),.halt(halt));

memory mem(.dataOut(CPU_dataIn),.dataIn(CPU_dataOut),.address(address),.reset(reset),.wr(wr),.clk(clk));
inMemory mem2(.dataOut(CPU_in_dataIn),.dataIn(CPU_in_dataOut),.address(in_address),.reset(reset),.wr(in_wr),.clk(clk));

//---------------------------------------------------------------------------------------------------------

//---------------------------------------------------------------------------------------------------------
`ifdef syn
initial $sdf_annotate ("np_sync.sdf", tff);
`endif
//---------------------------------------------------------------------------------------------------------
//begin the clk
initial
begin
  clk = 0;
  reset = 1;
  #(3*CYCLE) reset = 0;
end

always #(CYCLE/2) clk = ~clk;
//---------------------------------------------------------------------------------------------------------
always @(halt) begin
  if(halt)begin
    $display("halt");
    $finish;
  end
end
//---------------------------------------------------------------------------------------------------------

`ifdef syn
initial begin
	$dumpfile("np_sync.vcd");
	$dumpvars;
end
`else
initial begin
	$dumpfile("np.vcd");
	$dumpvars;
end
`endif

endmodule

np.vcd
$date
	Wed Dec 11 09:24:56 2019
$end
$version
	Icarus Verilog
$end
$timescale
	10ps
$end
$scope module test $end
$var wire 1 ! wr $end
$var wire 1 " in_wr $end
$var wire 12 # in_address [11:0] $end
$var wire 1 $ halt $end
$var wire 12 % address [11:0] $end
$var wire 32 & CPU_in_dataOut [31:0] $end
$var wire 32 ' CPU_in_dataIn [31:0] $end
$var wire 32 ( CPU_dataOut [31:0] $end
$var wire 32 ) CPU_dataIn [31:0] $end
$var reg 1 * clk $end
$var reg 1 + reset $end
$scope module mem $end
$var wire 1 * clk $end
$var wire 1 + reset $end
$var wire 1 ! wr $end
$var wire 32 , dataIn [31:0] $end
$var wire 12 - address [11:0] $end
$var reg 32 . dataOut [31:0] $end
$upscope $end
$scope module mem2 $end
$var wire 1 * clk $end
$var wire 1 + reset $end
$var wire 1 " wr $end
$var wire 32 / dataIn [31:0] $end
$var wire 12 0 address [11:0] $end
$var reg 32 1 dataOut [31:0] $end
$upscope $end
$scope module mnp $end
$var wire 1 * clk $end
$var wire 32 2 dataIn [31:0] $end
$var wire 32 3 in_dataIn [31:0] $end
$var wire 1 + reset $end
$var reg 12 4 address [11:0] $end
$var reg 32 5 dataOut [31:0] $end
$var reg 1 6 dir $end
$var reg 1 $ halt $end
$var reg 12 7 in_address [11:0] $end
$var reg 32 8 in_dataOut [31:0] $end
$var reg 1 " in_wr $end
$var reg 32 9 ir [31:0] $end
$var reg 2 : next_state [1:0] $end
$var reg 12 ; pc [11:0] $end
$var reg 12 < pc_r [11:0] $end
$var reg 5 = psr [4:0] $end
$var reg 5 > psr_r [4:0] $end
$var reg 33 ? result [32:0] $end
$var reg 33 @ result_r [32:0] $end
$var reg 32 A src1 [31:0] $end
$var reg 32 B src2 [31:0] $end
$var reg 2 C state [1:0] $end
$var reg 1 ! wr $end
$var integer 32 D i [31:0] $end
$scope function checkcond $end
$var reg 5 E ccode [4:0] $end
$var reg 1 F checkcond $end
$upscope $end
$scope function getdst $end
$var reg 32 G getdst [31:0] $end
$var reg 32 H in [31:0] $end
$upscope $end
$scope function getsrc $end
$var reg 32 I getsrc [31:0] $end
$var reg 32 J in [31:0] $end
$upscope $end
$scope task clearcondcode $end
$upscope $end
$scope task execute $end
$upscope $end
$scope task fetch $end
$upscope $end
$scope task setcondcode $end
$var reg 33 K res [32:0] $end
$upscope $end
$scope task write_result $end
$upscope $end
$upscope $end
$upscope $end
$enddefinitions $end
#0
$dumpvars
bx K
bx J
bx I
bx H
bx G
xF
bx E
bx D
bx C
bx B
bx A
bx @
bx ?
bx >
bx =
bx <
bx ;
bx :
bx 9
bx 8
bx 7
x6
bx 5
bx 4
bx 3
bx 2
bx 1
bx 0
bx /
bx .
bx -
bx ,
1+
0*
bx )
bx (
bx '
bx &
bx %
x$
bx #
x"
x!
$end
#500
b0 :
b0 =
b0 ?
b0 B
b0 A
b0 (
b0 ,
b0 5
b0 #
b0 0
b0 7
b0 %
b0 -
b0 4
0!
0"
0$
b0 ;
b0 >
b0 @
b0 <
b11 C
1*
#1000
0*
#1500
1*
#2000
0*
#2500
1*
#3000
0*
0+
#3500
b1 :
b0 9
b0 C
b0 '
b0 1
b0 3
1*
#4000
0*
#4500
b10 :
b1 C
1*
#5000
0*
#5500
b0 :
b1 ;
b10 C
1*
#6000
0*
#6500
b1 :
b1 #
b1 0
b1 7
b0 C
b1 <
1*
#7000
0*
#7500
b10 :
b11 ;
1F
b0 E
b10000000000000000000000000011 9
b1 C
b10000000000000000000000000011 '
b10000000000000000000000000011 1
b10000000000000000000000000011 3
1*
#8000
0*
#8500
b0 :
b11 #
b11 0
b11 7
b10 C
b11 <
1*
#9000
0*
#9500
b1 :
b111000000000000010000000000000 9
b0 C
b111000000000000010000000000000 '
b111000000000000010000000000000 1
b111000000000000010000000000000 3
1*
#10000
0*
#10500
b10 :
b10 ?
b1 C
1*
#11000
0*
#11500
b0 :
b100 ;
b110 =
b10 K
b10 C
b10 @
1*
#12000
0*
#12500
b1 :
b100 #
b100 0
b100 7
b110 >
b0 C
b100 <
1*
#13000
0*
#13500
b10 :
b100000000000 %
b100000000000 -
b100000000000 4
1!
b0 =
b100000000000000000100000000000 9
b1 C
b100000000000000000100000000000 '
b100000000000000000100000000000 1
b100000000000000000100000000000 3
1*
#14000
0*
#14500
b0 :
b101 ;
b110 =
b10 (
b10 ,
b10 5
b100000000000 %
b100000000000 -
b100000000000 4
1!
b0 >
b10 C
1*
#15000
0*
#15500
b1 :
b0 (
b0 ,
b0 5
b101 #
b101 0
b101 7
b0 %
b0 -
b0 4
0!
b110 >
b0 C
b101 <
1*
#16000
0*
#16500
b10 :
b0 ?
b0 =
b111000000000000000000000000000 9
b1 C
b111000000000000000000000000000 '
b111000000000000000000000000000 1
b111000000000000000000000000000 3
1*
#17000
0*
#17500
b0 :
b110 ;
b1010 =
b0 K
b0 >
b10 C
b0 @
1*
#18000
0*
#18500
b1 :
b110 #
b110 0
b110 7
b1010 >
b0 C
b110 <
1*
#19000
0*
#19500
b10 :
b100000000000 %
b100000000000 -
b100000000000 4
b0 =
b110000100000000000000000000000 9
b1 C
b110000100000000000000000000000 '
b110000100000000000000000000000 1
b110000100000000000000000000000 3
1*
#20000
0*
#20500
b0 :
b111 ;
b110 =
b10 K
b10 ?
b100000000000 %
b100000000000 -
b100000000000 4
b0 >
b10 C
b10 )
b10 .
b10 2
1*
#21000
0*
#21500
b1 :
b111 #
b111 0
b111 7
b0 %
b0 -
b0 4
b110 >
b0 C
b10 @
b111 <
1*
#22000
0*
#22500
b10 :
b0 ?
b0 =
b111000000000000000000000000000 9
b1 C
bx )
bx .
bx 2
b111000000000000000000000000000 '
b111000000000000000000000000000 1
b111000000000000000000000000000 3
1*
#23000
0*
#23500
b0 :
b1000 ;
b1010 =
b0 K
b0 >
b10 C
b0 @
1*
#24000
0*
#24500
b1 :
b1000 #
b1000 0
b1000 7
b1010 >
b0 C
b1000 <
1*
#25000
0*
#25500
b10 :
b100 ?
b0 G
b1001000000000000100000000000000 H
b100 A
b100 I
b1001000000000000100000000000000 J
b0 =
b1001000000000000100000000000000 9
b1 C
b1001000000000000100000000000000 '
b1001000000000000100000000000000 1
b1001000000000000100000000000000 3
1*
#26000
0*
#26500
b0 :
b1001 ;
b110 =
b100 K
b0 A
b0 >
b10 C
b100 @
1*
#27000
0*
#27500
b1 :
b1001 #
b1001 0
b1001 7
b110 >
b0 C
b1001 <
1*
#28000
0*
#28500
b10 :
b10 ?
b0 =
b111000000000000010000000000000 9
b1 C
b111000000000000010000000000000 '
b111000000000000010000000000000 1
b111000000000000010000000000000 3
1*
#29000
0*
#29500
b0 :
b1010 ;
b110 =
b10 K
b0 >
b10 C
b10 @
1*
#30000
0*
#30500
b1 :
b1010 #
b1010 0
b1010 7
b110 >
b0 C
b1010 <
1*
#31000
0*
#31500
b10 :
b1000 ?
b10 B
b10 G
b1011000000000000100000000000000 H
b100 A
b1011000000000000100000000000000 J
b0 =
b1011000000000000100000000000000 9
b1 C
b1011000000000000100000000000000 '
b1011000000000000100000000000000 1
b1011000000000000100000000000000 3
1*
#32000
0*
#32500
b0 :
b1011 ;
b110 =
b1000 K
b0 B
b0 A
b0 >
b10 C
b1000 @
1*
#33000
0*
#33500
b1 :
b1011 #
b1011 0
b1011 7
b110 >
b0 C
b1011 <
1*
#34000
0*
#34500
b10 :
b111111111111111111111111111110111 ?
b1000 A
b1000 I
b1100000000000000000000000000001 J
b0 =
b1100000000000000000000000000001 9
b1 C
b1100000000000000000000000000001 '
b1100000000000000000000000000001 1
b1100000000000000000000000000001 3
1*
#35000
0*
#35500
b0 :
b1100 ;
b10001 =
b111111111111111111111111111110111 K
b0 A
b0 >
b10 C
b111111111111111111111111111110111 @
1*
#36000
0*
#36500
b1 :
b1100 #
b1100 0
b1100 7
b10001 >
b0 C
b1100 <
1*
#37000
0*
#37500
b10 :
b1111 ?
b0 =
b111000000000001111000000000000 9
b1 C
b111000000000001111000000000000 '
b111000000000001111000000000000 1
b111000000000001111000000000000 3
1*
#38000
0*
#38500
b0 :
b1101 ;
b1111 K
b0 >
b10 C
b1111 @
1*
#39000
0*
#39500
b1 :
b1101 #
b1101 0
b1101 7
b0 C
b1101 <
1*
#40000
0*
#40500
b10 :
b0 ?
b111000000000000000000000000001 9
b1 C
b111000000000000000000000000001 '
b111000000000000000000000000001 1
b111000000000000000000000000001 3
1*
#41000
0*
#41500
b0 :
b1110 ;
b1010 =
b0 K
b10 C
b0 @
1*
#42000
0*
#42500
b1 :
b1110 #
b1110 0
b1110 7
b1010 >
b0 C
b1110 <
1*
#43000
0*
#43500
b10 :
b111111111111111111111111111111111 ?
b0 G
b10011000000000000001000000000001 H
b1 A
b1 I
b10011000000000000001000000000001 J
b0 =
b10011000000000000001000000000001 9
b1 C
b10011000000000000001000000000001 '
b10011000000000000001000000000001 1
b10011000000000000001000000000001 3
1*
#44000
0*
#44500
b0 :
b1111 ;
b10101 =
b111111111111111111111111111111111 K
b0 A
b0 >
b10 C
b111111111111111111111111111111111 @
1*
#45000
0*
#45500
b1 :
b1111 #
b1111 0
b1111 7
b10101 >
b0 C
b1111 <
1*
#46000
0*
#46500
b10 :
b11110 ?
b11111111111111111111111111111111 D
b1111 B
b1111 G
b1110000000000000001000000000000 H
b11111111111111111111111111111111 A
b11111111111111111111111111111111 I
b1110000000000000001000000000000 J
b0 =
b1110000000000000001000000000000 9
b1 C
b1110000000000000001000000000000 '
b1110000000000000001000000000000 1
b1110000000000000001000000000000 3
1*
#47000
0*
#47500
b0 :
b10000 ;
b10 =
b11110 K
b0 B
b0 A
b0 >
b10 C
b11110 @
1*
#48000
0*
#48500
b1 :
b10000 #
b10000 0
b10000 7
b10 >
b0 C
b10000 <
1*
#49000
0*
#49500
b10 :
b1111 ?
b1 D
b11110 B
b11110 G
b1111000000000000001000000000000 H
b1 A
b1 I
b1111000000000000001000000000000 J
b0 =
b1111000000000000001000000000000 9
b1 C
b1111000000000000001000000000000 '
b1111000000000000001000000000000 1
b1111000000000000001000000000000 3
1*
#50000
0*
#50500
b0 :
b10001 ;
b1111 K
b0 B
b0 A
b0 >
b10 C
b1111 @
1*
#51000
0*
#51500
b1 :
b10001 #
b10001 0
b10001 7
b0 C
b10001 <
1*
#52000
0*
#52500
b10 :
b1 ?
b111000000000000001000000000000 9
b1 C
b111000000000000001000000000000 '
b111000000000000001000000000000 1
b111000000000000001000000000000 3
1*
#53000
0*
#53500
b0 :
b10010 ;
b100 =
b1 K
b10 C
b1 @
1*
#54000
0*
#54500
b1 :
b10010 #
b10010 0
b10010 7
b100 >
b0 C
b10010 <
1*
#55000
0*
#55500
b10 :
b0 ?
b0 =
b111000000000000000000000000001 9
b1 C
b111000000000000000000000000001 '
b111000000000000000000000000001 1
b111000000000000000000000000001 3
1*
#56000
0*
#56500
b0 :
b10011 ;
b1010 =
b0 K
b0 >
b10 C
b0 @
1*
#57000
0*
#57500
b1 :
b10011 #
b10011 0
b10011 7
b1010 >
b0 C
b10011 <
1*
#58000
0*
#58500
b10 :
b111111111111111111111111111100001 ?
b0 G
b10011000000000011111000000000001 H
b11111 A
b11111 I
b10011000000000011111000000000001 J
b0 =
b10011000000000011111000000000001 9
b1 C
b10011000000000011111000000000001 '
b10011000000000011111000000000001 1
b10011000000000011111000000000001 3
1*
#59000
0*
#59500
b0 :
b10100 ;
b10101 =
b111111111111111111111111111100001 K
b0 A
b0 >
b10 C
b111111111111111111111111111100001 @
1*
#60000
0*
#60500
b1 :
b10100 #
b10100 0
b10100 7
b10101 >
b0 C
b10100 <
1*
#61000
0*
#61500
b10 :
b10000000000000000000000000000000 ?
b11111111111111111111111111100001 D
b1 B
b1 G
b1110000000000000001000000000000 H
b11111111111111111111111111100001 A
b11111111111111111111111111100001 I
b1110000000000000001000000000000 J
b0 =
b1110000000000000001000000000000 9
b1 C
b1110000000000000001000000000000 '
b1110000000000000001000000000000 1
b1110000000000000001000000000000 3
1*
#62000
0*
#62500
b0 :
b10101 ;
b10110 =
b10000000000000000000000000000000 K
b0 B
b0 A
b0 >
b10 C
b10000000000000000000000000000000 @
1*
#63000
0*
#63500
b1 :
b10101 #
b10101 0
b10101 7
b10110 >
b0 C
b10101 <
1*
#64000
0*
#64500
b10 :
b1000000000000000000000000000000 ?
b0 D
06
b1000000000000000000000000000000 B
b10000000000000000000000000000000 G
b10001000000000000001000000000000 H
b1 A
b1 I
b10001000000000000001000000000000 J
b0 =
b10001000000000000001000000000000 9
b1 C
b10001000000000000001000000000000 '
b10001000000000000001000000000000 1
b10001000000000000001000000000000 3
1*
#65000
0*
#65500
b0 :
b10110 ;
b110 =
b1000000000000000000000000000000 K
b0 B
b0 A
b0 >
b10 C
b1000000000000000000000000000000 @
1*
#66000
0*
#66500
b1 :
b10110 #
b10110 0
b10110 7
b110 >
b0 C
b10110 <
1*
#67000
0*
#67500
b10 :
b10000 ?
b0 =
b111000000000010000000000000000 9
b1 C
b111000000000010000000000000000 '
b111000000000010000000000000000 1
b111000000000010000000000000000 3
1*
#68000
0*
#68500
b0 :
b10111 ;
b110 =
b10000 K
b0 >
b10 C
b10000 @
1*
#69000
0*
#69500
b1 :
b10111 #
b10111 0
b10111 7
b110 >
b0 C
b10111 <
1*
#70000
0*
#70500
b10 :
b1100 ?
b10000 B
b10000 G
b10011000000000000100000000000000 H
b100 A
b100 I
b10011000000000000100000000000000 J
b0 =
b10011000000000000100000000000000 9
b1 C
b10011000000000000100000000000000 '
b10011000000000000100000000000000 1
b10011000000000000100000000000000 3
1*
#71000
0*
#71500
b0 :
b11000 ;
b10 =
b1100 K
b0 B
b0 A
b0 >
b10 C
b1100 @
1*
#72000
0*
#72500
b1 :
b11000 #
b11000 0
b11000 7
b10 >
b0 C
b11000 <
1*
#73000
0*
#73500
b10 :
b10000 ?
b0 =
b111000000000010000000000000000 9
b1 C
b111000000000010000000000000000 '
b111000000000010000000000000000 1
b111000000000010000000000000000 3
1*
#74000
0*
#74500
b0 :
b11001 ;
b110 =
b10000 K
b0 >
b10 C
b10000 @
1*
#75000
0*
#75500
b1 :
b11001 #
b11001 0
b11001 7
b110 >
b0 C
b11001 <
1*
#76000
0*
#76500
b10 :
b10001 ?
b0 =
b111000000000010001000000000001 9
b1 C
b111000000000010001000000000001 '
b111000000000010001000000000001 1
b111000000000010001000000000001 3
1*
#77000
0*
#77500
b0 :
b11010 ;
b10001 K
b0 >
b10 C
b10001 @
1*
#78000
0*
#78500
b1 :
b11010 #
b11010 0
b11010 7
b0 C
b11010 <
1*
#79000
0*
#79500
b10 :
b10000 B
b10100000000000000001000000000000 H
b10001 A
b10001 I
b10100000000000000001000000000000 J
b10100000000000000001000000000000 9
b1 C
b10100000000000000001000000000000 '
b10100000000000000001000000000000 1
b10100000000000000001000000000000 3
1*
#80000
0*
#80500
b0 :
b11011 ;
b0 B
b0 A
b10 C
1*
#81000
0*
#81500
b1 :
b11011 #
b11011 0
b11011 7
b0 C
b11011 <
1*
#82000
0*
#82500
b10 :
1$
b10111111111111111111111111111111 9
b1 C
b10111111111111111111111111111111 '
b10111111111111111111111111111111 1
b10111111111111111111111111111111 3
1*
